chos/__init__.py
chos/__main__.py
chos/sync/__init__.py
chos/sync/__main__.py
chos-1.0.dist-info/LICENSE
chos-1.0.dist-info/METADATA
chos-1.0.dist-info/WHEEL
chos-1.0.dist-info/top_level.txt
chos-1.0.dist-info/RECORD
