Metadata-Version: 2.1
Name: chos
Version: 1.0
Summary: Search your favorite songs/artists/playlists/genres, Get details and recommendations.
Home-page: https://t.me/execal
Author: odi
Author-email: ivuxey@gmail.com
License: MIT
Project-URL: Source, https://github.com/vauth
Project-URL: Bug Tracker, https://t.me/feelded
Keywords: spotify,recommendation,ml,music
Classifier: Programming Language :: Python :: 3
Classifier: License :: OSI Approved :: MIT License
Classifier: Operating System :: OS Independent
Requires-Python: >=3.5
License-File: LICENSE
Requires-Dist: requests
Requires-Dist: aiow
